pydsa
