Metadata-Version: 1.1
Name: pydsa
Version: 0.14
Summary: Python DSA library
Home-page: https://github.com/rrottmann/pydsa
Author: Reiner Rottmann
Author-email: reiner@rottmann.it
License: MIT License, see LICENSE
Keywords: crypto,DSA,signature
Platform: UNKNOWN
Classifier: License :: OSI Approved :: MIT License
Classifier: Programming Language :: Python
Classifier: Development Status :: 4 - Beta
Classifier: Intended Audience :: Developers
Classifier: Topic :: Internet
